setup.py
tim_distributions/Binomialdistribution.py
tim_distributions/Gaussiandistribution.py
tim_distributions/Generaldistribution.py
tim_distributions/__init__.py
tim_distributions.egg-info/PKG-INFO
tim_distributions.egg-info/SOURCES.txt
tim_distributions.egg-info/dependency_links.txt
tim_distributions.egg-info/not-zip-safe
tim_distributions.egg-info/top_level.txt