Metadata-Version: 1.0
Name: tim-distributions
Version: 0.1
Summary: Gaussian distributions
Home-page: UNKNOWN
Author: UNKNOWN
Author-email: clicklekan@gmail.com
License: UNKNOWN
Platform: UNKNOWN
